{
  "type": "minecraft:crafting_shapeless",
  "category": "misc",
  "ingredients": [
    {    "item": "ancindicators:numeric_indicator_item_equals"},
    {    "item": "ancindicators:numeric_indicator_item_equals"},
    {    "item": "ancindicators:numeric_indicator_item_equals"},
    {    "item": "ancindicators:numeric_indicator_item_equals"},
    {    "item": "ancindicators:numeric_indicator_item_equals"},
    {    "item": "ancindicators:numeric_indicator_item_equals"}
  ],
  "result": {    "item": "ancindicators:numeric_indicator_block_equals"  }
}